{
  "iphone_15_pro_max_data": {
    "brand": {
      "name": "Apple",
      "country": "United States",
      "website": "https://www.apple.com"
    },
    "category": {
      "name": "Smartphone",
      "parentId": null
    },
    "model": {
      "name": "iPhone 15 Pro Max 256GB",
      "releaseYear": 2023,
      "os": "IOS",
      "chipset": "Apple A17 Pro",
      "cpuCores": 6,
      "cpuMaxGhz": 3.78,
      "gpu": "Apple GPU (6-core graphics)",
      "displaySizeInch": 6.7,
      "displayResolution": "1290x2796",
      "displayRefreshHz": 120,
      "displayPanel": "Super Retina XDR OLED",
      "displayBrightnessNits": 2000,
      "glassProtection": "Ceramic Shield",
      "mainCameraMp": 48,
      "ultrawideCameraMp": 12,
      "telephotoMp": 12,
      "selfieCameraMp": 12,
      "video4k": true,
      "video8k": false,
      "batteryCapacityMah": 4422,
      "chargeWiredW": 20,
      "chargeWirelessW": 15,
      "reverseChargeW": null,
      "wifiVersion": "Wi-Fi 6E",
      "bluetoothVersion": "5.3",
      "nfc": true,
      "usbType": "Lightning",
      "gpsSystems": "GPS, GLONASS, Galileo, QZSS, BeiDou",
      "cellular5g": true,
      "uwb": true,
      "irBlaster": false,
      "isActive": true
    },
    "product": {
      "sku": "IPHONE15PROMAX256GB",
      "name": "iPhone 15 Pro Max 256GB",
      "unitPrice": 30390000,
      "isActive": true,
      "attributes": {
        "color": "Blue Titanium",
        "storage": "256GB",
        "ram": "8GB",
        "originalPrice": 30390000,
        "salePrice": 29390000,
        "discount": "3%",
        "rating": 4.9,
        "soldCount": "243.4k",
        "imageUrl": "https://cdn.tgdd.vn/Products/Images/42/305658/iphone-15-pro-max-blue-thumbnew-600x600.jpg",
        "productUrl": "https://www.thegioididong.com/dtdd/iphone-15-pro-max"
      }
    },
    "variant": {
      "color": "Blue Titanium",
      "ramGb": 8,
      "storageGb": 256,
      "sku": "IPHONE15PROMAX256GB-BLUE",
      "isActive": true
    }
  }
}

